net_promoter_score/__init__.py
net_promoter_score/admin.py
net_promoter_score/apps.py
net_promoter_score/forms.py
net_promoter_score/middleware.py
net_promoter_score/migrations/0001_initial.py
net_promoter_score/migrations/0002_promoterscore_source.py
net_promoter_score/migrations/__init__.py
net_promoter_score/models.py
net_promoter_score/settings.py
net_promoter_score/signals.py
net_promoter_score/urls.py
net_promoter_score/utils.py
net_promoter_score/views.py
django_nps-1.3.dist-info/METADATA
django_nps-1.3.dist-info/WHEEL
django_nps-1.3.dist-info/licenses/LICENSE
django_nps-1.3.dist-info/RECORD
