Metadata-Version: 2.4
Name: django-nps
Version: 1.3
Summary: Django app supporting Net Promoter Score (NPS) surveys.
License: MIT
License-File: LICENSE
Author: YunoJuno
Author-email: code@yunojuno.com
Maintainer: YunoJuno
Maintainer-email: code@yunojuno.com
Requires-Python: >=3.12,<4.0
Classifier: Environment :: Web Environment
Classifier: Framework :: Django :: 5.2
Classifier: Framework :: Django :: 6.0
Classifier: License :: OSI Approved :: MIT License
Classifier: Operating System :: OS Independent
Classifier: Programming Language :: Python :: 3
Classifier: Programming Language :: Python :: 3.12
Classifier: Programming Language :: Python :: 3.13
Classifier: Programming Language :: Python :: 3.14
Classifier: Programming Language :: Python :: 3 :: Only
Requires-Dist: django (>=5.2,<7.0)
Project-URL: Homepage, https://github.com/yunojuno/django-nps
Project-URL: Repository, https://github.com/yunojuno/django-nps
